point_in_time/__init__.py
point_in_time/errors.py
point_in_time/logging.py
point_in_time/util.py
point_in_time-0.0.0.dist-info/METADATA
point_in_time-0.0.0.dist-info/WHEEL
point_in_time-0.0.0.dist-info/top_level.txt
point_in_time-0.0.0.dist-info/RECORD
